py2openai/__init__.py
py2openai/bind_kwargs.py
py2openai/create_type.py
py2openai/executable.py
py2openai/functionschema.py
py2openai/py.typed
py2openai/schema_generators.py
py2openai/typedefs.py
py2openai-1.0.1.dist-info/WHEEL
py2openai-1.0.1.dist-info/METADATA
py2openai-1.0.1.dist-info/RECORD
