Metadata-Version: 2.3
Name: py2openai
Version: 1.0.1
Summary: Create OpenAI-compatible function schemas from python functions
Keywords: 
Author: Philipp Temminghoff
Author-email: Philipp Temminghoff <philipptemminghoff@googlemail.com>
License: MIT License
Classifier: Development Status :: 4 - Beta
Classifier: Framework :: Pydantic
Classifier: Framework :: Pydantic :: 2
Classifier: Intended Audience :: Developers
Classifier: Operating System :: OS Independent
Classifier: Programming Language :: Python :: 3
Classifier: Programming Language :: Python :: 3 :: Only
Classifier: Programming Language :: Python :: 3.12
Classifier: Programming Language :: Python :: 3.13
Classifier: Programming Language :: Python :: 3.14
Classifier: Topic :: Documentation
Classifier: Topic :: Software Development
Classifier: Topic :: Utilities
Classifier: Typing :: Typed
Requires-Dist: docstring-parser>=0.16
Requires-Dist: pydantic
Requires-Python: >=3.13
Project-URL: Code coverage, https://app.codecov.io/gh/phil65/py2openai
Project-URL: Discussions, https://github.com/phil65/py2openai/discussions
Project-URL: Documentation, https://phil65.github.io/py2openai/
Project-URL: Issues, https://github.com/phil65/py2openai/issues
Project-URL: Source, https://github.com/phil65/py2openai
